procedure_data_tool/__init__.py
procedure_data_tool/main.py
procedure_data_tool/utils/WRPS-new-logo.png
procedure_data_tool/utils/WRPS_LOGO.png
procedure_data_tool/utils/__init__.py
procedure_data_tool/utils/docwriter.py
procedure_data_tool/utils/excelData.py
procedure_data_tool/utils/graph.py
procedure_data_tool/utils/line.py
procedure_data_tool/utils/node.py
procedure_data_tool/utils/nozzle.py
procedure_data_tool/utils/pit.py
procedure_data_tool/utils/pump.py
procedure_data_tool/utils/split.py
procedure_data_tool/utils/tankreturn.py
procedure_data_tool/utils/valve.py
procedure_data_tool/utils/valve2.py
procedure_data_tool/utils/valve3.py
procedure_data_tool/utils/__pycache__/__init__.cpython-311.pyc
procedure_data_tool/utils/__pycache__/docwriter.cpython-311.pyc
procedure_data_tool/utils/__pycache__/dropleg.cpython-311.pyc
procedure_data_tool/utils/__pycache__/excelData.cpython-311.pyc
procedure_data_tool/utils/__pycache__/graph.cpython-311.pyc
procedure_data_tool/utils/__pycache__/line.cpython-311.pyc
procedure_data_tool/utils/__pycache__/node.cpython-311.pyc
procedure_data_tool/utils/__pycache__/nozzle.cpython-311.pyc
procedure_data_tool/utils/__pycache__/pit.cpython-311.pyc
procedure_data_tool/utils/__pycache__/pump.cpython-311.pyc
procedure_data_tool/utils/__pycache__/split.cpython-311.pyc
procedure_data_tool/utils/__pycache__/tankreturn.cpython-311.pyc
procedure_data_tool/utils/__pycache__/valve.cpython-311.pyc
procedure_data_tool/utils/__pycache__/valve2.cpython-311.pyc
procedure_data_tool/utils/__pycache__/valve3.cpython-311.pyc
procedure_data_tool-0.1.1.dist-info/LICENSE.txt
procedure_data_tool-0.1.1.dist-info/METADATA
procedure_data_tool-0.1.1.dist-info/WHEEL
procedure_data_tool-0.1.1.dist-info/entry_points.txt
procedure_data_tool-0.1.1.dist-info/top_level.txt
procedure_data_tool-0.1.1.dist-info/RECORD
