Metadata-Version: 2.1
Name: procedure-data-tool
Version: 0.1.1
Summary: Reference tool for DST Waste Transfer Procedures Based on automatically generated route
Author: Josue Estrada
Author-email: jramiroem@gmail.com
License: MIT
License-File: LICENSE.txt
Requires-Dist: openpyxl
Requires-Dist: python-docx
Requires-Dist: networkx
Requires-Dist: matplotlib
Requires-Dist: indexed
Requires-Dist: scipy
Requires-Dist: ttkthemes
